braintrust_adk/__init__.py
tests/__init__.py
tests/conftest.py
tests/test_adk.py
tests/test_mcp_tool.py
braintrust_adk-0.3.1.dist-info/METADATA
braintrust_adk-0.3.1.dist-info/WHEEL
braintrust_adk-0.3.1.dist-info/top_level.txt
braintrust_adk-0.3.1.dist-info/RECORD
