Metadata-Version: 2.4
Name: braintrust-adk
Version: 0.3.1
Summary: Braintrust Google ADK integration
Author-email: Braintrust <info@braintrust.dev>
License: Apache-2.0
Project-URL: Homepage, https://www.braintrust.dev
Project-URL: Repository, https://github.com/braintrustdata/braintrust-sdk
Keywords: braintrust,google-adk,adk,agents,ai,llm,tracing
Classifier: Development Status :: 4 - Beta
Classifier: License :: OSI Approved :: Apache Software License
Classifier: Programming Language :: Python :: 3.10
Classifier: Programming Language :: Python :: 3.11
Requires-Python: >=3.10
Requires-Dist: braintrust>=0.4.1
Requires-Dist: google-adk>=1.14.1
Requires-Dist: wrapt>=1.17.3
